LICENSE
MANIFEST.in
README.md
setup.py
ChIA_Rep.egg-info/PKG-INFO
ChIA_Rep.egg-info/SOURCES.txt
ChIA_Rep.egg-info/dependency_links.txt
ChIA_Rep.egg-info/requires.txt
ChIA_Rep.egg-info/top_level.txt
chia_rep/__init__.py
chia_rep/chia_rep.py
chia_rep/chrom_loop_data.py
chia_rep/genome_loop_data.py
chia_rep/util.c
chia_rep/util.pyx
test/test_chia_rep.py
test/test_package.py