Metadata-Version: 2.1
Name: ChIA-Rep
Version: 3.1.1
Summary: A package for measuring reproducibility of ChIA-PET data.
Home-page: https://github.com/c0ver/chia_rep
Author: Henry Zhang
Author-email: henrybzhang.99@gmail.com
License: MIT
Platform: UNKNOWN
Classifier: Programming Language :: Python :: 3
Classifier: License :: OSI Approved :: MIT License
Classifier: Operating System :: OS Independent
Requires-Python: >=3.6
